{
    "quizName": "Name",
    "quizDesc": "Description Here",
    "shuffleOrder": true,
    "allowTraversal": true,
    "allowAIGrading": true,
    "classId": "Iixrqf3iIsgVkZOlYCMl",
    "authors": [
        "Author A",
        "Author B"
    ],
    "questions": [
        {
            "questionId": "0",
            "questionType": "MC",
            "questionTitle": "Nerds",
            "questionBody": "What is the capital of Wisconsin?",
            "embeds": [
                "https://media.istockphoto.com/id/839295596/photo/six-pre-teen-friends-piggybacking-in-a-park-close-up-portrait.jpg?s=612x612&w=0&k=20&c=MWkFYzpRSvO1dRql3trV4k6ECO-rTy4HgF8OxrtUkH8=",
                "FiREBASE STORAGE IMAGE"
            ],
            "correctAnswers": [
                0
            ],
            "answers": [
                {
                    "answerId": 0,
                    "answerBody": "Madison",
                    "answerIcon": "iconName"
                },
                {
                    "answerId": 1,
                    "answerBody": "Milwaukee",
                    "answerIcon": "iconName"
                },
                {
                    "answerId": 2,
                    "answerBody": "Ozaukee",
                    "answerIcon": "iconName"
                },
                {
                    "answerId": 3,
                    "answerBody": "Washington D.C.",
                    "answerIcon": "iconName"
                }
            ]
        },
        {
            "questionId": "1",
            "questionType": "TF",
            "questionTitle": "What is the evaluation of this text here?",
            "questionBody": "The correct answer is True.",
            "correctAnswer": true
        },
        {
            "questionId": "2",
            "questionType": "SA",
            "questionTitle": "Wisconsin Capital",
            "questionBody": "What is the capital of Wisconsin?",
            "singleWord": true,
            "answers": [
                "Madison"
            ]
        },
        {
            "questionId": "3",
            "questionType": "LA",
            "questionTitle": "Wisconsin Capital",
            "questionBody": "Write a bit about the capital of Wisconsin?",
            "singleWord": true,
            "criteria": "Needs to say the capital is madison, and needs to mention the University of Wisconsin that resides in madison."
        }
    ]
}